padlock/__init__.py
padlock/errors.py
padlock/manager.py
padlock/py.typed
padlock/backends/__init__.py
padlock/backends/base.py
padlock/backends/etcd.py
padlock/backends/memory.py
python_padlock-0.1.3.dist-info/METADATA
python_padlock-0.1.3.dist-info/WHEEL
python_padlock-0.1.3.dist-info/licenses/LICENSE
python_padlock-0.1.3.dist-info/RECORD
