Metadata-Version: 2.4
Name: python-padlock
Version: 0.1.3
Summary: A Python library for distributed locking via a variety of backends.
Project-URL: repository, https://gitlab.com/emergentmethods/python-padlock
Author-email: Tim Pogue <tim@emergentmethods.ai>
License: MIT
License-File: LICENSE
Requires-Python: <4.0,>=3.10
Provides-Extra: etcd
Requires-Dist: etcd-client-py>=0.4.0; extra == 'etcd'
Provides-Extra: zookeeper
Requires-Dist: aiozk>=0.31.1; extra == 'zookeeper'
